qzone_api/__init__.py
qzone_api/api/__init__.py
qzone_api/api/api_base.py
qzone_api/api/api_feed.py
qzone_api/api/api_parms.py
qzone_api/api/api_zone.py
qzone_api/login/__init__.py
qzone_api/login/cookie_handler.py
qzone_api/login/qrcode.py
qzone_api/utils/__init__.py
qzone_api/utils/html_parser.py
qzone_api/utils/others.py
qzone_api-0.0.10.dist-info/LICENSE
qzone_api-0.0.10.dist-info/METADATA
qzone_api-0.0.10.dist-info/WHEEL
qzone_api-0.0.10.dist-info/top_level.txt
qzone_api-0.0.10.dist-info/RECORD
