Metadata-Version: 2.1
Name: qzone-api
Version: 0.0.10
Summary: QQ空间API封装
Home-page: https://github.com/huanxin996/qzone_api
Author: Huan Xin
Author-email: mc.xiaolang@foxmail.com
Classifier: Programming Language :: Python :: 3
Classifier: License :: OSI Approved :: MIT License
Classifier: Operating System :: OS Independent
License-File: LICENSE
Requires-Dist: aiohttp>=3.11.11
Requires-Dist: lxml>=5.3.0
Requires-Dist: loguru>=0.7.3
Requires-Dist: requests<=2.32.3
Requires-Dist: pyzbar>=0.1.9
Requires-Dist: Pillow>=10.2.0
Requires-Dist: qrcode>=7.4.2
